minPath/Errors.py
minPath/Objects.py
minPath/__init__.py
minPath-0.1.3.dist-info/LICENCE.txt
minPath-0.1.3.dist-info/METADATA
minPath-0.1.3.dist-info/WHEEL
minPath-0.1.3.dist-info/top_level.txt
minPath-0.1.3.dist-info/RECORD
